getobjcols/__init__.py
getobjcols/obj_fi.py
getobjcols/.ipynb_checkpoints/Untitled-checkpoint.ipynb
getobjcols-0.0.1.dist-info/METADATA
getobjcols-0.0.1.dist-info/WHEEL
getobjcols-0.0.1.dist-info/licenses/LICENSE.txt
getobjcols-0.0.1.dist-info/RECORD
