Metadata-Version: 2.1
Name: getobjcols
Version: 0.0.1
Summary: A package to get a list of object columns in your pandas dataframe
Author-email: Rohit Sharan <rohit.sharan2008@gmail.com>
License-File: LICENSE.txt
Classifier: License :: OSI Approved :: MIT License
Classifier: Operating System :: OS Independent
Classifier: Programming Language :: Python :: 3
Requires-Python: >=3.7
